rest_filter_qp/__init__.py
rest_filter_qp/config.py
rest_filter_qp/filters.py
rest_filter_qp/methods.py
rest_filter_qp/validators.py
rest_filter_qp-1.2.1.dist-info/LICENSE
rest_filter_qp-1.2.1.dist-info/METADATA
rest_filter_qp-1.2.1.dist-info/WHEEL
rest_filter_qp-1.2.1.dist-info/top_level.txt
rest_filter_qp-1.2.1.dist-info/RECORD
