Metadata-Version: 2.1
Name: rest-filter-qp
Version: 1.2.1
Summary: A package for filtering any objects in django models
Home-page: https://github.com/mahmoodrezaei/rest-filter-qp
Author: Mahmoud Rezaei
Author-email: mahmoudrezaei74@gmail.com
License: UNKNOWN
Project-URL: Bug Tracker, https://github.com/mahmoodrezaei/rest-filter-qp
Platform: UNKNOWN
Classifier: Programming Language :: Python :: 3
Classifier: License :: OSI Approved :: MIT License
Classifier: Operating System :: OS Independent
Requires-Python: >=3.6
License-File: LICENSE
